playwright_scenographer-1.0.1.dist-info/licenses/LICENSE.txt
scenographer/__init__.py
scenographer/_shared/__init__.py
scenographer/_shared/core/__init__.py
scenographer/_shared/core/_browser_storage.py
scenographer/_shared/core/_default_storage.py
scenographer/_shared/core/_use_web_extensions.py
scenographer/async_api/__init__.py
scenographer/async_api/core/__init__.py
scenographer/async_api/core/_browser_feed.py
scenographer/async_api/core/_use_feed.py
scenographer/async_api/core/_web_store.py
scenographer/async_api/stores/__init__.py
scenographer/async_api/stores/_chrome.py
scenographer/async_api/stores/_local.py
scenographer/async_api/stores/_stores.py
scenographer/async_api/utils/__init__.py
scenographer/async_api/utils/_bytes_from_file.py
scenographer/sync_api/__init__.py
scenographer/sync_api/core/__init__.py
scenographer/sync_api/core/_browser_feed.py
scenographer/sync_api/core/_use_feed.py
scenographer/sync_api/core/_web_store.py
scenographer/sync_api/stores/__init__.py
scenographer/sync_api/stores/_chrome.py
scenographer/sync_api/stores/_local.py
scenographer/sync_api/stores/_stores.py
scenographer/sync_api/utils/__init__.py
scenographer/sync_api/utils/_bytes_from_file.py
playwright_scenographer-1.0.1.dist-info/METADATA
playwright_scenographer-1.0.1.dist-info/WHEEL
playwright_scenographer-1.0.1.dist-info/top_level.txt
playwright_scenographer-1.0.1.dist-info/RECORD
